odoo/addons/product_supplierinfo_stock_picking_type/README.rst
odoo/addons/product_supplierinfo_stock_picking_type/__init__.py
odoo/addons/product_supplierinfo_stock_picking_type/__manifest__.py
odoo/addons/product_supplierinfo_stock_picking_type/i18n/es.po
odoo/addons/product_supplierinfo_stock_picking_type/i18n/it.po
odoo/addons/product_supplierinfo_stock_picking_type/i18n/product_supplierinfo_stock_picking_type.pot
odoo/addons/product_supplierinfo_stock_picking_type/models/__init__.py
odoo/addons/product_supplierinfo_stock_picking_type/models/product_product.py
odoo/addons/product_supplierinfo_stock_picking_type/models/product_supplierinfo.py
odoo/addons/product_supplierinfo_stock_picking_type/models/purchase_order.py
odoo/addons/product_supplierinfo_stock_picking_type/readme/CONFIGURE.rst
odoo/addons/product_supplierinfo_stock_picking_type/readme/CONTRIBUTORS.rst
odoo/addons/product_supplierinfo_stock_picking_type/readme/DESCRIPTION.rst
odoo/addons/product_supplierinfo_stock_picking_type/readme/USAGE.rst
odoo/addons/product_supplierinfo_stock_picking_type/static/description/icon.png
odoo/addons/product_supplierinfo_stock_picking_type/static/description/index.html
odoo/addons/product_supplierinfo_stock_picking_type/tests/__init__.py
odoo/addons/product_supplierinfo_stock_picking_type/tests/test_product_supplierinfo_stock_picking_type.py
odoo/addons/product_supplierinfo_stock_picking_type/views/product_supplierinfo_view.xml
odoo14_addon_product_supplierinfo_stock_picking_type-14.0.1.0.1.dev12.dist-info/METADATA
odoo14_addon_product_supplierinfo_stock_picking_type-14.0.1.0.1.dev12.dist-info/WHEEL
odoo14_addon_product_supplierinfo_stock_picking_type-14.0.1.0.1.dev12.dist-info/top_level.txt
odoo14_addon_product_supplierinfo_stock_picking_type-14.0.1.0.1.dev12.dist-info/RECORD
